napari_ndev/__init__.py
napari_ndev/__main__.py
napari_ndev/_napari_reader.py
napari_ndev/_plate_mapper.py
napari_ndev/_settings.py
napari_ndev/_version.py
napari_ndev/helpers.py
napari_ndev/image_overview.py
napari_ndev/measure.py
napari_ndev/morphology.py
napari_ndev/napari.yaml
napari_ndev/ndev_settings.yaml
napari_ndev/nimage.py
napari_ndev/_tests/__init__.py
napari_ndev/_tests/conftest.py
napari_ndev/_tests/test_helpers.py
napari_ndev/_tests/test_image_overview.py
napari_ndev/_tests/test_import.py
napari_ndev/_tests/test_main.py
napari_ndev/_tests/test_measure.py
napari_ndev/_tests/test_morphology.py
napari_ndev/_tests/test_napari_reader.py
napari_ndev/_tests/test_nimage.py
napari_ndev/_tests/test_plate_mapper.py
napari_ndev/_tests/test_settings.py
napari_ndev/_tests/resources/0T-4C-0Z-7pos.czi
napari_ndev/_tests/resources/RGB.tiff
napari_ndev/_tests/resources/cells3d2ch.tiff
napari_ndev/_tests/resources/measure_props_Labels.csv
napari_ndev/_tests/resources/measure_props_Labels_grouped.csv
napari_ndev/_tests/resources/nDev-logo-small.png
napari_ndev/_tests/resources/Apoc/Annotations/SPF-4MM-22 slide 9-S6_Top Slide_TR2_p00_0_A01f00d0.tiff
napari_ndev/_tests/resources/Apoc/Classifiers/newlabels_pixel_classifier.cl
napari_ndev/_tests/resources/Apoc/Classifiers/newlabels_pixel_classifier.log.txt
napari_ndev/_tests/resources/Apoc/Classifiers/test_classifier.cl
napari_ndev/_tests/resources/Apoc/Classifiers/test_classifier.log.txt
napari_ndev/_tests/resources/Apoc/Images/SPF-4MM-22 slide 9-S6_Top Slide_TR2_p00_0_A01f00d0.tiff
napari_ndev/_tests/resources/Apoc/Images/SPF-4MM-22 slide 9-S9_Top Slide_TR5_p00_0_A01f00d0.tiff
napari_ndev/_tests/resources/Apoc/OutputLabels/SPF-4MM-22 slide 9-S6_Top Slide_TR2_p00_0_A01f00d0.tiff
napari_ndev/_tests/resources/Apoc/OutputLabels/SPF-4MM-22 slide 9-S9_Top Slide_TR5_p00_0_A01f00d0.tiff
napari_ndev/_tests/resources/Apoc/OutputLabels/log.txt
napari_ndev/_tests/resources/Measure/.log.txt
napari_ndev-0.11.8.dist-info/licenses/LICENSE
napari_ndev-0.11.8.dist-info/METADATA
napari_ndev-0.11.8.dist-info/WHEEL
napari_ndev-0.11.8.dist-info/entry_points.txt
napari_ndev-0.11.8.dist-info/top_level.txt
napari_ndev-0.11.8.dist-info/RECORD
