Metadata-Version: 2.4
Name: napari-ndev
Version: 0.11.8
Summary: napari widgets to (batch) process images from start to finish.
Author-email: Tim Monko <timmonko@gmail.com>
License: BSD-3-Clause
Project-URL: Bug Tracker, https://github.com/TimMonko/napari-ndev/issues
Project-URL: Documentation, https://ndev-kit.github.io/
Project-URL: Source Code, https://github.com/TimMonko/napari-ndev
Classifier: Development Status :: 3 - Alpha
Classifier: Framework :: napari
Classifier: Intended Audience :: Education
Classifier: Intended Audience :: Science/Research
Classifier: License :: OSI Approved :: BSD License
Classifier: Operating System :: OS Independent
Classifier: Programming Language :: Python
Classifier: Programming Language :: Python :: 3
Classifier: Programming Language :: Python :: 3 :: Only
Classifier: Programming Language :: Python :: 3.9
Classifier: Programming Language :: Python :: 3.10
Classifier: Programming Language :: Python :: 3.11
Classifier: Programming Language :: Python :: 3.12
Classifier: Topic :: Scientific/Engineering :: Image Processing
Classifier: Topic :: Scientific/Engineering :: Visualization
Classifier: Topic :: Software Development :: User Interfaces
Classifier: Topic :: Software Development :: Libraries :: Python Modules
Classifier: Topic :: Utilities
Requires-Python: >=3.9
License-File: LICENSE
Requires-Dist: numpy<2.0,>=1.26
Requires-Dist: siphash24>=1.6
Requires-Dist: magicgui>=0.8.3
Requires-Dist: magic-class
Requires-Dist: napari[optional]>=0.4.19
Requires-Dist: apoc
Requires-Dist: pyclesperanto-prototype
Requires-Dist: pyclesperanto
Requires-Dist: dask
Requires-Dist: napari-workflows
Requires-Dist: napari-pyclesperanto-assistant
Requires-Dist: napari-segment-blobs-and-things-with-membranes
Requires-Dist: natsort
Requires-Dist: seaborn
Requires-Dist: stackview
Requires-Dist: tifffile<2025.2.18,>=2023.3.15
Requires-Dist: scikit-image>=0.18.0
Requires-Dist: ngff-zarr>0.10.0
Requires-Dist: zarr<3
Requires-Dist: bioio>=1.1.0
Requires-Dist: bioio-base==1.0.4
Requires-Dist: bioio-imageio>=1
Requires-Dist: bioio-tifffile>=1
Requires-Dist: bioio-ome-tiff>=1
Requires-Dist: bioio-ome-zarr>=1
Requires-Dist: bioio-nd2>=1
Requires-Dist: matplotlib-scalebar>=0.8.1
Provides-Extra: testing
Requires-Dist: pytest; extra == "testing"
Requires-Dist: pytest-cov; extra == "testing"
Requires-Dist: tox; extra == "testing"
Requires-Dist: tox-uv; extra == "testing"
Requires-Dist: pytest-qt; extra == "testing"
Requires-Dist: napari[all]; extra == "testing"
Requires-Dist: pyqt5; extra == "testing"
Requires-Dist: bioio-czi>=1.0.1; extra == "testing"
Requires-Dist: napari-ndev[extras]; extra == "testing"
Provides-Extra: docs
Requires-Dist: mkdocs; extra == "docs"
Requires-Dist: mkdocs-autorefs; extra == "docs"
Requires-Dist: mkdocs-material; extra == "docs"
Requires-Dist: mkdocstrings; extra == "docs"
Requires-Dist: mkdocstrings-python; extra == "docs"
Requires-Dist: mkdocs-jupyter; extra == "docs"
Requires-Dist: mkdocs-pdf; extra == "docs"
Requires-Dist: mkdocs-spellcheck[all]; extra == "docs"
Requires-Dist: mkdocs-literate-nav; extra == "docs"
Requires-Dist: mkdocs-table-reader-plugin; extra == "docs"
Requires-Dist: black; extra == "docs"
Provides-Extra: dev
Requires-Dist: ruff; extra == "dev"
Requires-Dist: pre-commit; extra == "dev"
Requires-Dist: napari-ndev[testing]; extra == "dev"
Requires-Dist: napari-ndev[docs]; extra == "dev"
Provides-Extra: qtpy-backend
Requires-Dist: napari-ndev[pyqt6]; extra == "qtpy-backend"
Provides-Extra: pyqt6
Requires-Dist: napari[pyqt6]; extra == "pyqt6"
Provides-Extra: pyqt5
Requires-Dist: napari[pyqt5]; extra == "pyqt5"
Provides-Extra: pyside
Requires-Dist: napari[pyside]; extra == "pyside"
Provides-Extra: extras
Requires-Dist: napari-simpleitk-image-processing; extra == "extras"
Provides-Extra: gpl-extras
Requires-Dist: bioio-czi>=1.0.1; extra == "gpl-extras"
Requires-Dist: bioio-lif>=1; extra == "gpl-extras"
Provides-Extra: all
Requires-Dist: napari-ndev[qtpy-backend]; extra == "all"
Requires-Dist: napari-ndev[extras]; extra == "all"
Requires-Dist: napari-ndev[gpl_extras]; extra == "all"
Dynamic: license-file
